ovos_solver_llmcpp/__init__.py
ovos_solver_llmcpp/engine.py
ovos_solver_llmcpp/version.py
ovos_solver_llmcpp_plugin-0.0.0a3.dist-info/LICENSE
ovos_solver_llmcpp_plugin-0.0.0a3.dist-info/METADATA
ovos_solver_llmcpp_plugin-0.0.0a3.dist-info/WHEEL
ovos_solver_llmcpp_plugin-0.0.0a3.dist-info/entry_points.txt
ovos_solver_llmcpp_plugin-0.0.0a3.dist-info/top_level.txt
ovos_solver_llmcpp_plugin-0.0.0a3.dist-info/zip-safe
ovos_solver_llmcpp_plugin-0.0.0a3.dist-info/RECORD
