Metadata-Version: 2.1
Name: ovos-solver-llmcpp-plugin
Version: 0.0.0a3
Summary: A question solver plugin for ovos
Home-page: https://github.com/OpenVoiceOS/ovos-solver-plugin-llmcpp
Author: jarbasai
Author-email: jarbasai@mailfence.com
License: MIT
Keywords: ovos plugin utterance fallback query
Platform: UNKNOWN
Requires-Dist: neon-solvers
